pywhyllm/__init__.py
pywhyllm/helpers.py
pywhyllm/prompts.py
pywhyllm/protocols/__init__.py
pywhyllm/protocols/estimator.py
pywhyllm/protocols/identifier.py
pywhyllm/protocols/modeler.py
pywhyllm/protocols/validator.py
pywhyllm/suggesters/__init__.py
pywhyllm/suggesters/identification_suggester.py
pywhyllm/suggesters/model_suggester.py
pywhyllm/suggesters/simple_identification_suggester.py
pywhyllm/suggesters/simple_model_suggester.py
pywhyllm/suggesters/tuebingen_model_suggester.py
pywhyllm/suggesters/validation_suggester.py
pywhyllm-0.1.dist-info/LICENSE
pywhyllm-0.1.dist-info/METADATA
pywhyllm-0.1.dist-info/WHEEL
pywhyllm-0.1.dist-info/RECORD
