Metadata-Version: 2.3
Name: pywhyllm
Version: 0.1
Summary: PyWhyLLM enables usage of large language models in the causal inference pipeline. It integrates with existing PyWhy libraries such as DoWhy and causallearn.
License: MIT
Keywords: large language model,causal discovery,causality,machine-learning,causal-inference,statistics,graphical-model
Author: PyWhy Community
Author-email: amshar@microsoft.com
Requires-Python: >=3.9,<3.13
Classifier: Development Status :: 4 - Beta
Classifier: License :: OSI Approved :: MIT License
Classifier: Programming Language :: Python :: 3
Classifier: Programming Language :: Python :: 3.9
Classifier: Programming Language :: Python :: 3.10
Classifier: Programming Language :: Python :: 3.11
Classifier: Programming Language :: Python :: 3.12
Requires-Dist: guidance (>=0.2)
Requires-Dist: networkx (<=3.2.1)
Requires-Dist: openai (>=1.70)
Requires-Dist: pydantic (>=2.11)
Project-URL: Documentation, https://py-why.github.io/pywhy-llm
Project-URL: Repository, https://github.com/py-why/pywhy-llm
